meringue/__init__.py
meringue/meringue.py
pymeringue-1.0.0.dist-info/METADATA
pymeringue-1.0.0.dist-info/WHEEL
pymeringue-1.0.0.dist-info/top_level.txt
pymeringue-1.0.0.dist-info/RECORD
