Metadata-Version: 2.1
Name: pymeringue
Version: 1.0.0
Summary: A port of Meringue (https://github.com/stiive/meringue) for Python.
Home-page: https://github.com/stiive/py-meringue
Author: Beckett Normington
Author-email: beckett@chatter-social.com
License: BSD
Platform: UNKNOWN
Classifier: License :: OSI Approved :: BSD License
Classifier: Programming Language :: Python :: 3
Classifier: Programming Language :: Python :: 3.7
